math_131_numerics/__init__.py
math_131_numerics-0.0.2.dist-info/LICENSE
math_131_numerics-0.0.2.dist-info/WHEEL
math_131_numerics-0.0.2.dist-info/METADATA
math_131_numerics-0.0.2.dist-info/RECORD
