Metadata-Version: 2.1
Name: math_131_numerics
Version: 0.0.2
Summary: Package including standard numerical methods taught in numerics class at UC
Home-page: https://www.github.com/carvalhocamille/math_131_numerics
License: UNKNOWN
Author: Camille Carvalho
Author-email: ccarvalho3@ucmerced.edu
Classifier: License :: OSI Approved :: MIT License
